ghga_service_commons/__init__.py
ghga_service_commons/__main__.py
ghga_service_commons/py.typed
ghga_service_commons/api/__init__.py
ghga_service_commons/api/api.py
ghga_service_commons/api/di.py
ghga_service_commons/api/mock_router.py
ghga_service_commons/api/testing.py
ghga_service_commons/auth/__init__.py
ghga_service_commons/auth/context.py
ghga_service_commons/auth/ghga.py
ghga_service_commons/auth/jwt_auth.py
ghga_service_commons/auth/policies.py
ghga_service_commons/http/__init__.py
ghga_service_commons/http/correlation.py
ghga_service_commons/httpyexpect/__init__.py
ghga_service_commons/httpyexpect/base_exception.py
ghga_service_commons/httpyexpect/models.py
ghga_service_commons/httpyexpect/validation.py
ghga_service_commons/httpyexpect/client/__init__.py
ghga_service_commons/httpyexpect/client/custom_types.py
ghga_service_commons/httpyexpect/client/exceptions.py
ghga_service_commons/httpyexpect/client/mapping.py
ghga_service_commons/httpyexpect/client/translator.py
ghga_service_commons/httpyexpect/server/__init__.py
ghga_service_commons/httpyexpect/server/exceptions.py
ghga_service_commons/httpyexpect/server/handlers/__init__.py
ghga_service_commons/httpyexpect/server/handlers/fastapi_.py
ghga_service_commons/transports/__init__.py
ghga_service_commons/transports/config.py
ghga_service_commons/transports/factory.py
ghga_service_commons/transports/proxy_handling.py
ghga_service_commons/transports/ratelimiting.py
ghga_service_commons/transports/retry.py
ghga_service_commons/utils/__init__.py
ghga_service_commons/utils/context.py
ghga_service_commons/utils/crypt.py
ghga_service_commons/utils/crypt4gh.py
ghga_service_commons/utils/files.py
ghga_service_commons/utils/jwt_helpers.py
ghga_service_commons/utils/multinode_storage.py
ghga_service_commons/utils/simple_token.py
ghga_service_commons/utils/temp_files.py
ghga_service_commons/utils/utc_dates.py
ghga_service_commons-6.1.0.dist-info/licenses/LICENSE
ghga_service_commons-6.1.0.dist-info/METADATA
ghga_service_commons-6.1.0.dist-info/WHEEL
ghga_service_commons-6.1.0.dist-info/top_level.txt
ghga_service_commons-6.1.0.dist-info/RECORD
