Metadata-Version: 2.4
Name: ghga_service_commons
Version: 6.1.0
Summary: A library that contains common functionality used in services of GHGA
Author-email: "German Human Genome Phenome Archive (GHGA)" <contact@ghga.de>
License: Apache 2.0
Project-URL: Repository, https://github.com/ghga-de/ghga-service-commons
Classifier: Development Status :: 1 - Planning
Classifier: Operating System :: POSIX :: Linux
Classifier: Programming Language :: Python :: 3.10
Classifier: Programming Language :: Python :: 3.11
Classifier: Programming Language :: Python :: 3.12
Classifier: Programming Language :: Python :: 3.13
Classifier: License :: OSI Approved :: Apache Software License
Classifier: Topic :: Internet :: WWW/HTTP :: HTTP Servers
Classifier: Topic :: Software Development :: Libraries
Classifier: Intended Audience :: Developers
Requires-Python: >=3.10
License-File: LICENSE
Requires-Dist: pydantic<3,>=2
Provides-Extra: api
Requires-Dist: fastapi<0.121,>=0.115.4; extra == "api"
Requires-Dist: uvicorn[standard]<0.39,>=0.35; extra == "api"
Requires-Dist: ghga-service-commons[http,objectstorage]; extra == "api"
Provides-Extra: http
Requires-Dist: httpx<0.29,>=0.27; extra == "http"
Provides-Extra: auth
Requires-Dist: jwcrypto<2,>=1.5.6; extra == "auth"
Requires-Dist: pydantic[email]<3,>=2; extra == "auth"
Provides-Extra: crypt
Requires-Dist: pynacl<2,>=1.5; extra == "crypt"
Requires-Dist: crypt4gh<2,>=1.6; extra == "crypt"
Provides-Extra: dev
Requires-Dist: requests<3,>=2.31; extra == "dev"
Provides-Extra: objectstorage
Requires-Dist: hexkit>=7.2.1; extra == "objectstorage"
Provides-Extra: transports
Requires-Dist: hishel<0.2,>=0.1.1; extra == "transports"
Requires-Dist: tenacity<10,>=9.0.0; extra == "transports"
Requires-Dist: ghga-service-commons[http]; extra == "transports"
Provides-Extra: all
Requires-Dist: ghga-service-commons[api,auth,crypt,dev,http,objectstorage,transports]; extra == "all"
Dynamic: license-file
